scribe/__init__.py
scribe/cli/__init__.py
scribe/cli/helpers.py
scribe/cli/main.py
scribe/core/__init__.py
scribe/core/context_factory.py
scribe/core/exceptions.py
scribe/core/generator.py
scribe/core/settings.py
scribe/core/template_finder.py
scribe/core/typings.py
scribe/models/__init__.py
scribe/models/context.py
scribe/models/custom.py
scribe/models/templates.py
scribe/util/__init__.py
scribe/util/loader.py
scribe/util/logger.py
scribe/util/schema_loader.py
scribe_templates-0.3.1.dist-info/METADATA
scribe_templates-0.3.1.dist-info/WHEEL
scribe_templates-0.3.1.dist-info/entry_points.txt
scribe_templates-0.3.1.dist-info/RECORD
