Metadata-Version: 2.3
Name: scribe-templates
Version: 0.3.1
Summary: Rapid DOCX generation from Jinja2 templates – YAML + pydantic + Typer.
Author: Alex
Requires-Python: >=3.10
Classifier: Programming Language :: Python :: 3
Classifier: Programming Language :: Python :: 3.10
Classifier: Programming Language :: Python :: 3.11
Classifier: Programming Language :: Python :: 3.12
Classifier: Programming Language :: Python :: 3.13
Requires-Dist: coverage (>=7.9.2,<8.0.0)
Requires-Dist: docxtpl (>=0.20.1,<0.21.0)
Requires-Dist: hypothesis (>=6.135.32,<7.0.0)
Requires-Dist: openpyxl (>=3.1.5,<4.0.0)
Requires-Dist: pandas (>=2.3.1,<3.0.0)
Requires-Dist: pandas-stubs (>=2.3.0.250703,<3.0.0.0)
Requires-Dist: pydantic (>=2.11.7,<3.0.0)
Requires-Dist: pydantic-settings (>=2.10.1,<3.0.0)
Requires-Dist: pytest (>=8.4.1,<9.0.0)
Requires-Dist: pyyaml (>=6.0.2,<7.0.0)
Requires-Dist: typer (>=0.16.0,<0.17.0)
Requires-Dist: types-pyyaml (>=6.0.12.20250516,<7.0.0.0)
